codoniser/__init__.py
codoniser/main.py
codoniser/plotting/__init__.py
codoniser/plotting/barchart.py
codoniser/plotting/heatmap.py
codoniser/utils/__init__.py
codoniser/utils/classes.py
codoniser/utils/errors.py
codoniser/utils/io.py
codoniser/utils/parser.py
codoniser-1.0.1.dist-info/LICENSE
codoniser-1.0.1.dist-info/METADATA
codoniser-1.0.1.dist-info/WHEEL
codoniser-1.0.1.dist-info/entry_points.txt
codoniser-1.0.1.dist-info/top_level.txt
codoniser-1.0.1.dist-info/RECORD
