Metadata-Version: 2.2
Name: codoniser
Version: 1.0.1
Summary: A python package to analyse and optimise codons.
Home-page: https://github.com/DrBoothTJ/codoniser
Author: Thomas J. Booth
Author-email: thoboo@biosustain.dtu.dk
License: GNU General Public License v3.0
Requires-Python: >=3.7
License-File: LICENSE
Requires-Dist: biopython>=1.83
Requires-Dist: matplotlib>=3.10.0
Requires-Dist: seaborn>=0.13.2
Requires-Dist: scipy>=1.15.1
Dynamic: author
Dynamic: author-email
Dynamic: description
Dynamic: description-content-type
Dynamic: home-page
Dynamic: license
Dynamic: requires-dist
Dynamic: requires-python
Dynamic: summary
